LICENSE.txt
MANIFEST.in
README.md
setup.cfg
setup.py
bonghoa.egg-info/PKG-INFO
bonghoa.egg-info/SOURCES.txt
bonghoa.egg-info/dependency_links.txt
bonghoa.egg-info/top_level.txt
sample/__init__.py
test/__init__.py
test/test_simple.py